README.md
pyproject.toml
setup.py
mobio/sdks/mail_client/__init__.py
mobio/sdks/mail_client/consts.py
mobio/sdks/mail_client/errors.py
mobio/sdks/mail_client/folder.py
mobio/sdks/mail_client/imap_utf7.py
mobio/sdks/mail_client/mailbox.py
mobio/sdks/mail_client/message.py
mobio/sdks/mail_client/query.py
mobio/sdks/mail_client/utils.py
mobio/sdks/mail_client/talon/__init__.py
mobio/sdks/mail_client/talon/constants.py
mobio/sdks/mail_client/talon/html_quotations.py
mobio/sdks/mail_client/talon/quotations.py
mobio/sdks/mail_client/talon/utils.py
mobio_mail_client_sdk_test.egg-info/PKG-INFO
mobio_mail_client_sdk_test.egg-info/SOURCES.txt
mobio_mail_client_sdk_test.egg-info/dependency_links.txt
mobio_mail_client_sdk_test.egg-info/namespace_packages.txt
mobio_mail_client_sdk_test.egg-info/requires.txt
mobio_mail_client_sdk_test.egg-info/top_level.txt