Metadata-Version: 2.1
Name: mobio-mail-client-sdk-test
Version: 0.1.18
Summary: Mobio mail client SDK
Home-page: https://github.com/mobiovn
Author: MOBIO
Author-email: contact@mobio.vn
License: MIT
Project-URL: Source, https://github.com/mobiovn
Keywords: mobio,mail client,imap
Classifier: Development Status :: 3 - Alpha
Classifier: Intended Audience :: Developers
Classifier: Topic :: Software Development :: Build Tools
Classifier: License :: OSI Approved :: MIT License
Classifier: Programming Language :: Python :: 3
Classifier: Programming Language :: Python :: 3.6
Classifier: Programming Language :: Python :: 3.7
Classifier: Programming Language :: Python :: 3.8
Classifier: Programming Language :: Python :: 3.9
Classifier: Programming Language :: Python :: 3 :: Only
Requires-Python: >=3
Requires-Dist: chardet>=1.0.1
Requires-Dist: faust-cchardet>=0.3.5
Requires-Dist: cssselect
Requires-Dist: html5lib
Requires-Dist: lxml>=2.3.3
Requires-Dist: regex>=1
Requires-Dist: six>=1.10.0
